windowsworld_api/__init__.py
windowsworld_api/api.py
windowsworld_api-1.0.0.dist-info/LICENSE
windowsworld_api-1.0.0.dist-info/METADATA
windowsworld_api-1.0.0.dist-info/WHEEL
windowsworld_api-1.0.0.dist-info/top_level.txt
windowsworld_api-1.0.0.dist-info/RECORD
