Metadata-Version: 2.2
Name: windowsworld-api
Version: 1.0.0
Summary: A Python client for the Windows World API
Author: WindowsWorldCartoon
Author-email: windowsworldcartoon@gmail.com
Classifier: Programming Language :: Python :: 3
Classifier: License :: OSI Approved :: MIT License
Classifier: Operating System :: OS Independent
License-File: LICENSE
Requires-Dist: requests
Dynamic: author
Dynamic: author-email
Dynamic: classifier
Dynamic: requires-dist
Dynamic: summary
